SEQ/pcupdate/pcupdate_64.v
module pc_update_64 (input clk, input [3:0] icode, input [63:0] valC, input [63:0] valM, input [63:0] valP, input cnd, output reg [63:0] new_pc);

    always@(*)
    begin
        case (icode)
            4'b0000: new_pc = 63'b0;  // halt
            4'b0001: new_pc = valP;   // nop
            4'b0010: new_pc = valP;   // cmovXX
            4'b0011: new_pc = valP;   // irmovq
            4'b0100: new_pc = valP;   // rmmovq
            4'b0101: new_pc = valP;   // mrmovq
            4'b0110: new_pc = valP;   // Opq
            4'b0111: begin            // jXX
                if(cnd == 1)
                    new_pc = valC;
                else
                    new_pc = valP;
            end
            4'b1000: new_pc = valC;   // call
            4'b1001: new_pc = valM;   // ret
            4'b1010: new_pc = valP;   // pushq
            4'b1011: new_pc = valP;   // popq
            default: new_pc = valP;
        endcase
    end

endmodule

SEQ/pcupdate/pcupdate_64_tb.v
`include "pcupdate_64.v"

module pcupdate_64_tb;

    reg clk;
    reg [3:0] icode;
    reg cnd;
    reg [63:0] valC, valM, valP;
    wire [63:0] new_pc;

    pc_update_64 uut2 (clk, icode, valC, valM, valP, cnd, new_pc);

    initial begin
        $dumpfile("pcupdate_output.vcd");
        $dumpvars(0,pcupdate_64_tb);
    end

    always #5 clk = ~clk;

    initial begin
        $monitor($time,"ns: icode:%d \t new-pc: %d", icode,new_pc); 

        clk = 1'b1; 
        cnd = 1'b1;

        valP = 64'd112;
        valC = 64'd100;
        valM = 64'd17;

        icode = 4'd0;

        #10;
        valP = 64'd1;
        valC = 64'd2;
        valM = 64'd3;

        icode = 4'd1;

        #10;
        valP = 64'd11;
        valC = 64'd22;
        valM = 64'd33;

        icode = 4'd2;

        #10;
        valP = 64'd1;
        valC = 64'd2;
        valM = 64'd3;

        icode = 4'd3; 
        
        #10;
        valP = 64'd11;
        valC = 64'd22;
        valM = 64'd33;

        icode = 4'd4; 
        
        #10;
        valP = 64'd1;
        valC = 64'd2;
        valM = 64'd3;

        icode = 4'd5; 
        
        #10;
        valP = 64'd11;
        valC = 64'd22;
        valM = 64'd33;

        icode = 4'd6; 
        
        #10;
        valP = 64'd1;
        valC = 64'd2;
        valM = 64'd3;

        icode = 4'd7; 

        #10;
        valP = 64'd11;
        valC = 64'd22;
        valM = 64'd33;

        icode = 4'd8;

        #10;
        valP = 64'd1;
        valC = 64'd2;
        valM = 64'd3;

        icode = 4'd9;

        #10;
        valP = 64'd11;
        valC = 64'd22;
        valM = 64'd33;

        icode = 4'd10;

        #10;
        valP = 64'd1;
        valC = 64'd2;
        valM = 64'd3;

        icode = 4'd11; #10;

        $finish;
    end
    
endmodule

SEQ/pcupdate/pcupdate_output.vcd
$date
	Sun Feb 18 15:57:19 2024
$end
$version
	Icarus Verilog
$end
$timescale
	1s
$end
$scope module pcupdate_64_tb $end
$var wire 64 ! new_pc [63:0] $end
$var reg 1 " clk $end
$var reg 1 # cnd $end
$var reg 4 $ icode [3:0] $end
$var reg 64 % valC [63:0] $end
$var reg 64 & valM [63:0] $end
$var reg 64 ' valP [63:0] $end
$scope module uut2 $end
$var wire 1 " clk $end
$var wire 1 # cnd $end
$var wire 4 ( icode [3:0] $end
$var wire 64 ) valC [63:0] $end
$var wire 64 * valM [63:0] $end
$var wire 64 + valP [63:0] $end
$var reg 64 , new_pc [63:0] $end
$upscope $end
$upscope $end
$enddefinitions $end
#0
$dumpvars
b0 ,
b1110000 +
b10001 *
b1100100 )
b0 (
b1110000 '
b10001 &
b1100100 %
b0 $
1#
1"
b0 !
$end
#5
0"
#10
b1 !
b1 ,
1"
b1 $
b1 (
b11 &
b11 *
b10 %
b10 )
b1 '
b1 +
#15
0"
#20
b1011 !
b1011 ,
1"
b10 $
b10 (
b100001 &
b100001 *
b10110 %
b10110 )
b1011 '
b1011 +
#25
0"
#30
b1 !
b1 ,
1"
b11 $
b11 (
b11 &
b11 *
b10 %
b10 )
b1 '
b1 +
#35
0"
#40
b1011 !
b1011 ,
1"
b100 $
b100 (
b100001 &
b100001 *
b10110 %
b10110 )
b1011 '
b1011 +
#45
0"
#50
b1 !
b1 ,
1"
b101 $
b101 (
b11 &
b11 *
b10 %
b10 )
b1 '
b1 +
#55
0"
#60
b1011 !
b1011 ,
1"
b110 $
b110 (
b100001 &
b100001 *
b10110 %
b10110 )
b1011 '
b1011 +
#65
0"
#70
b10 !
b10 ,
1"
b111 $
b111 (
b11 &
b11 *
b10 %
b10 )
b1 '
b1 +
#75
0"
#80
b10110 !
b10110 ,
1"
b1000 $
b1000 (
b100001 &
b100001 *
b10110 %
b10110 )
b1011 '
b1011 +
#85
0"
#90
b11 !
b11 ,
1"
b1001 $
b1001 (
b11 &
b11 *
b10 %
b10 )
b1 '
b1 +
#95
0"
#100
b1011 !
b1011 ,
1"
b1010 $
b1010 (
b100001 &
b100001 *
b10110 %
b10110 )
b1011 '
b1011 +
#105
0"
#110
b1 !
b1 ,
1"
b1011 $
b1011 (
b11 &
b11 *
b10 %
b10 )
b1 '
b1 +
