SEQ/decode/decode_64.v
module decode_64 (input clk, input [3:0] icode, input [3:0] rA, input [3:0] rB, input [63:0] [0:14] R, output reg [63:0] valA, output reg [63:0] valB);

    always @(icode)
    begin
        case (icode)
            // halt -> do nothing
            // nop -> do nothing
            4'b0010: begin   // cmovXX
                valA = R[rA];
                valB = 63'b0;
            end
            // irmovq -> do nothing
            4'b0100: begin   // rmmovq
                valA = R[rA];
                valB = R[rB];
            end
            4'b0101: begin   // mrmovq
                valB = R[rB];
            end
            4'b0110: begin   // Opq
                valA = R[rA];
                valB = R[rB];
            end
            // jXX -> do nothing
            4'b1000: begin   // call
                valB = R[4];       
            end
            4'b1001: begin   // ret
                valA = R[4];
                valB = R[4];
            end
            4'b1010: begin   // pushq
                valA = R[rA];
                valB = R[4];
            end
            4'b1011: begin   // popq
                valA = R[4];
                valB = R[4];
            end
            default: ;
        endcase

    end
endmodule

SEQ/decode/decode_64_tb.v
`include "decode_64.v"

module decode_64_tb;

    reg clk;
    reg [3:0] icode;
    reg [3:0] rA, rB;
    reg [63:0] [0:14] R;
    wire [63:0] valA;
    wire [63:0] valB;

    decode_64 uut1 (clk, icode, rA, rB, R, valA, valB);

    initial begin
        $dumpfile("decode_output.vcd");
        $dumpvars(0,decode_64_tb);
    end

    always #5 clk = ~clk;

    initial begin
        $monitor($time,"ns: icode:%d \t rA:%d;  rB:%d \t valA:%d;  valB:%d", icode,rA,rB,valA,valB); 

        R[0] = 64'd999;
        R[1] = 64'd888;
        R[2] = 64'd777;
        R[3] = 64'd666;
        R[4] = 64'd555;
        R[5] = 64'd444;
        R[6] = 64'd333;
        R[7] = 64'd222;
        R[8] = 64'd111;
        R[9] = 64'd10;
        R[10] = 64'd20;
        R[11] = 64'd30;
        R[12] = 64'd40;
        R[13] = 64'd50;
        R[14] = 64'd60;

        clk = 1'b1; 

        icode = 4'd0;
        rA = 4'd1;
        rB = 4'd12;

        #10;
        icode = 4'd1;
        rA = 4'd0;
        rB = 4'd2;

        #10;
        icode = 4'd2;
        rA = 4'd10;
        rB = 4'd1;

        #10;
        rA = 4'd13;
        rB = 4'd12;
        icode = 4'd3; 
        
        #10;
        rA = 4'd2;
        rB = 4'd3;
        icode = 4'd4; 
        
        #10;
        rA = 4'd13;
        rB = 4'd5;
        icode = 4'd5; 
        
        #10;
        rA = 4'd10;
        rB = 4'd7;
        icode = 4'd6; 
        
        #10;
        rA = 4'd6;
        rB = 4'd7;
        icode = 4'd7; 

        #10;
        rA = 4'd13;
        rB = 4'd7;
        icode = 4'd8;

        #10;
        rA = 4'd11;
        rB = 4'd12;
        icode = 4'd9;

        #10;
        rA = 4'd5;
        rB = 4'd2;
        icode = 4'd10;

        #10;
        rA = 4'd1;
        rB = 4'd7;
        icode = 4'd11;

        $finish;
    end
    
endmodule

SEQ/decode/decode_output.vcd
$date
	Sun Feb 18 15:56:01 2024
$end
$version
	Icarus Verilog
$end
$timescale
	1s
$end
$scope module decode_64_tb $end
$var wire 64 ! valB [63:0] $end
$var wire 64 " valA [63:0] $end
$var reg 960 # R [959:0] $end
$var reg 1 $ clk $end
$var reg 4 % icode [3:0] $end
$var reg 4 & rA [3:0] $end
$var reg 4 ' rB [3:0] $end
$scope module uut1 $end
$var wire 960 ( R [959:0] $end
$var wire 1 $ clk $end
$var wire 4 ) icode [3:0] $end
$var wire 4 * rA [3:0] $end
$var wire 4 + rB [3:0] $end
$var reg 64 , valA [63:0] $end
$var reg 64 - valB [63:0] $end
$upscope $end
$upscope $end
$enddefinitions $end
#0
$dumpvars
bx -
bx ,
b1100 +
b1 *
b0 )
bx000000000111100000000000110010000000000101000000000000011110000000000010100000000000001010000000001101111000000011011110000000101001101000000110111100000001000101011000001010011010000001100001001000001101111000000001111100111 (
b1100 '
b1 &
b0 %
1$
bx000000000111100000000000110010000000000101000000000000011110000000000010100000000000001010000000001101111000000011011110000000101001101000000110111100000001000101011000001010011010000001100001001000001101111000000001111100111 #
bx "
bx !
$end
#5
0$
#10
1$
b10 '
b10 +
b0 &
b0 *
b1 %
b1 )
#15
0$
#20
b0 !
b0 -
b10100 "
b10100 ,
1$
b1 '
b1 +
b1010 &
b1010 *
b10 %
b10 )
#25
0$
#30
1$
b11 %
b11 )
b1100 '
b1100 +
b1101 &
b1101 *
#35
0$
#40
b1010011010 !
b1010011010 -
b1100001001 "
b1100001001 ,
1$
b100 %
b100 )
b11 '
b11 +
b10 &
b10 *
#45
0$
#50
b110111100 !
b110111100 -
1$
b101 %
b101 )
b101 '
b101 +
b1101 &
b1101 *
#55
0$
#60
b11011110 !
b11011110 -
b10100 "
b10100 ,
1$
b110 %
b110 )
b111 '
b111 +
b1010 &
b1010 *
#65
0$
#70
1$
b111 %
b111 )
b110 &
b110 *
#75
0$
#80
b1000101011 !
b1000101011 -
1$
b1000 %
b1000 )
b1101 &
b1101 *
#85
0$
#90
b1000101011 "
b1000101011 ,
1$
b1001 %
b1001 )
b1100 '
b1100 +
b1011 &
b1011 *
#95
0$
#100
b110111100 "
b110111100 ,
1$
b1010 %
b1010 )
b10 '
b10 +
b101 &
b101 *
#105
0$
#110
b1000101011 "
b1000101011 ,
1$
b1011 %
b1011 )
b111 '
b111 +
b1 &
b1 *
